{
    "ingestIt": {
        "metadata": {
            "callback": null, 
            "help_url": "https://debug.github.io/vfxClientToolkit/html/configuration.html#ingest-it",
            "enabled": true, 
            "name": "Ingest It", 
            "file": "vfxCTK_config_ingestIt", 
            "description": "etc"
        }, 
        "settings": {
            "email_recipients": {
                "pretty_name": "Email Recipients", 
                "data_type": "list", 
                "callback": null, 
                "type": "Group", 
                "tooltip": "All the recipients that will receive ingest notification mail.", 
                "value": null
            }, 
            "incoming_root": {
                "pretty_name": "Incoming Directory Root", 
                "data_type": "path", 
                "callback": {
                "func": "browseForIncoming", 
                "module": "vfxClientToolkit.configs.utils.ingestIt", 
                "label": "Browse"
                }, 
                "type": "Group", 
                "tooltip": "Directory path of all of the recieved packages.", 
                "value": null
            }
        }
    }
}
